spyderbi/__init__.py
spyderbi/main.py
spyderbi/simpleinfo.py
spyderbi-0.1.2.dist-info/METADATA
spyderbi-0.1.2.dist-info/WHEEL
spyderbi-0.1.2.dist-info/top_level.txt
spyderbi-0.1.2.dist-info/RECORD
