Metadata-Version: 2.1
Name: spyderbi
Version: 0.1.2
Summary: a library for who want to use bilibili to research,maybe in the near future,if you find any problem.you can send email to
Home-page: UNKNOWN
Author: UNKNOWN
Author-email: UNKNOWN
License: UNKNOWN
Keywords: bilibili
Platform: UNKNOWN
